who_installed/__init__.py
who_installed/main.py
who_installed-1.0.1.dist-info/METADATA
who_installed-1.0.1.dist-info/WHEEL
who_installed-1.0.1.dist-info/entry_points.txt
who_installed-1.0.1.dist-info/licenses/LICENSE
who_installed-1.0.1.dist-info/RECORD
